renkumls/__init__.py
renkumls/plugin.py
renku_mls-0.4.0.dist-info/LICENSE
renku_mls-0.4.0.dist-info/METADATA
renku_mls-0.4.0.dist-info/WHEEL
renku_mls-0.4.0.dist-info/entry_points.txt
renku_mls-0.4.0.dist-info/top_level.txt
renku_mls-0.4.0.dist-info/RECORD
